zoomeyesearch/__init__.py
zoomeyesearch/zoomeyesearch.py
zoomeyesearch/banner/__init__.py
zoomeyesearch/banner/banner.py
zoomeyesearch/barchart/barchart.py
zoomeyesearch/config/__init__.py
zoomeyesearch/config/config.py
zoomeyesearch/gitutils/__init__.py
zoomeyesearch/gitutils/gitutils.py
zoomeyesearch/help/__init__.py
zoomeyesearch/help/help.py
zoomeyesearch/logger/__init__.py
zoomeyesearch/logger/logger.py
zoomeyesearch/save/__init__.py
zoomeyesearch/save/save.py
zoomeyesearch/search/__init__.py
zoomeyesearch/search/search.py
zoomeyesearch/subdomain/__init__.py
zoomeyesearch/subdomain/subdomain.py
zoomeyesearch/utils/__init__.py
zoomeyesearch/utils/utils.py
zoomeyesearch/version/__init__.py
zoomeyesearch/version/version.py
zoomeyesearch/zoomeyeauth/__init__.py
zoomeyesearch/zoomeyeauth/zoomeyeauth.py
zoomeyesearch/zoomeyegpt/__init__.py
zoomeyesearch/zoomeyegpt/zoomeyegpt.py
zoomeyesearch/zoomeyelogin/__init__.py
zoomeyesearch/zoomeyelogin/zoomeyelogin.py
zoomeyesearch/zoomeyestats/__init__.py
zoomeyesearch/zoomeyestats/zoomeyestats.py
zoomeyesearch-1.0.0.dist-info/METADATA
zoomeyesearch-1.0.0.dist-info/WHEEL
zoomeyesearch-1.0.0.dist-info/entry_points.txt
zoomeyesearch-1.0.0.dist-info/licenses/LICENSE
zoomeyesearch-1.0.0.dist-info/RECORD
