Metadata-Version: 2.4
Name: zoomeyesearch
Version: 1.0.0
Summary: A powerful CLI tool that uses ZoomEye to search exposed services, gather intelligence, and automate reconnaissance.
Project-URL: Homepage, https://github.com/RevoltSecurities/ZoomeyeSearch
Project-URL: Documentation, https://github.com/RevoltSecurities/ZoomeyeSearch/wiki
Project-URL: Repository, https://github.com/RevoltSecurities/ZoomeyeSearch
Project-URL: Issues, https://github.com/RevoltSecurities/ZoomeyeSearch/issues
Author-email: "D. Sanjai Kumar" <bughunterz0047@gmail.com>, "Gokul.V" <th3gokul@gmail.com>
Maintainer-email: "D. Sanjai Kumar" <bughunterz0047@gmail.com>, "Gokul.V" <th3gokul@gmail.com>
License: MIT
License-File: LICENSE
Classifier: Development Status :: 5 - Production/Stable
Classifier: Environment :: Console
Classifier: Intended Audience :: Developers
Classifier: Intended Audience :: Information Technology
Classifier: License :: OSI Approved :: MIT License
Classifier: Programming Language :: Python :: 3.13
Classifier: Topic :: Security
Classifier: Topic :: Software Development :: Libraries
Classifier: Topic :: Utilities
Requires-Python: >=3.13
Requires-Dist: aiofiles>=24.1.0
Requires-Dist: appdirs>=1.4.4
Requires-Dist: art>=6.5
Requires-Dist: click>=8.2.1
Requires-Dist: colorama>=0.4.6
Requires-Dist: fake-useragent>=2.2.0
Requires-Dist: httpx>=0.28.1
Requires-Dist: playwright>=1.52.0
Requires-Dist: pyyaml>=6.0.2
Requires-Dist: rich>=14.0.0
